{"topic_id":9992,"word_level_id":2,"tag_id":0,"word":"microscopic","word_audio":"microscopic.mp3","word_variants":"microscopically,microscopical","image_file":"c_i_9992_2_0_3_150804150707.jpg","accent":"/ˌmaɪkrəˈskɑːpɪk/","mean_cn":"adj. 极小的；用显微镜可见的","mean_en":"able to be seen only through a microscope :extremely small","word_etyma":"microscop(e)显微镜 + ic形容词后缀 → microscopic 显微镜可见的，精微的","short_phrase":"microscopic life","deformation_img":"20140917_11_31_47_750_v3.png","sentence":"The student is taking a microscopic examination of the cells.","sentence_trans":"这个学生正在对细胞进行显微镜观察。","sentence_phrase":"microscopic examination","sentence_audio":"c_sa_9992_2_0_5_150812095654.aac","cloze_data":{"syllable":"mi-cro-scop-ic","cloze":"mi-cr[o]-sc[o]p-ic","options":["a|e|i|u","a|e|i|u"],"tips":[["cr[o]ci","micr[o]"],["sc[o]pic","geosc[o]pic"]]}}